Workbook

Sheet Raw_Data
A1: Date | B1: Month | C1: Month_Num | D1: Category | E1: Vendor_Service | F1: Description | G1: Amount | H1: Payment_Mode | I1: Phase
A2: 2026-05-05 | B2: May | C2: 5 | D2: Website Development | E2: PixelCraft Technologies | F2: UI/UX design advance payment | G2: 250000 | H2: Bank Transfer | I2: Setup
A3: 2026-05-10 | B3: May | C3: 5 | D3: Branding | E3: CreativeHive Studio | F3: Logo design & brand kit | G3: 75000 | H3: UPI | I3: Setup
A4: 2026-05-18 | B4: May | C4: 5 | D4: Domain & Hosting | E4: CloudNet Solutions | F4: Hosting + SSL + domain | G4: 48000 | H4: Credit Card | I4: Setup
A5: 2026-05-25 | B5: May | C5: 5 | D5: Recruitment | E5: HireSphere HR | F5: Hiring support | G5: 120000 | H5: Bank Transfer | I5: Setup
A6: 2026-06-02 | B6: Jun | C6: 6 | D6: Product Photography | E6: Studio Vogue | F6: Catalogue shoot for 500 SKUs | G6: 320000 | H6: Bank Transfer | I6: Launch Prep
A7: 2026-06-08 | B7: Jun | C7: 6 | D7: Inventory Purchase | E7: UrbanTex Suppliers | F7: Initial inventory batch | G7: 750000 | H7: RTGS | I7: Launch Prep
A8: 2026-06-16 | B8: Jun | C8: 6 | D8: Payment Gateway | E8: Razorpay Business | F8: Merchant onboarding | G8: 35000 | H8: UPI | I8: Launch Prep
A9: 2026-06-25 | B9: Jun | C9: 6 | D9: Logistics Setup | E9: ShipRocket Enterprise | F9: Shipping integration | G9: 110000 | H9: Bank Transfer | I9: Launch Prep
A10: 2026-07-05 | B10: Jul | C10: 7 | D10: Marketing | E10: Meta Ads India | F10: Instagram & Facebook ads | G10: 200000 | H10: Credit Card | I10: Go-Live

Sheet KPI_Summary
A1: 📊 EXPENSE ANALYSIS — EXECUTIVE DASHBOARD
A2: Startup Launch Expenditure | May – July 2026 | Source: Cleaned_Expenses
A4: KEY PERFORMANCE INDICATORS
A5: Total Spend | D5: Avg. Transaction | G5: Largest Expense | J5: Total Transactions
A6: =SUM(Raw_Data!G2:G10) -> 1908000 | D6: =AVERAGE(Raw_Data!G2:G10) -> 212000 | G6: =MAX(Raw_Data!G2:G10) -> 750000 | J6: =COUNTA(Raw_Data!A2:A10) -> 9
A7: 9 transactions | D7: Per vendor | G7: Inventory batch | J7: May–Jul 2026
A9: May Spend | D9: June Spend | G9: July Spend | J9: Pending Reimb.
A10: =SUMIF(Raw_Data!B2:B10,"May",Raw_Data!G2:G10) -> 493000 | D10: =SUMIF(Raw_Data!B2:B10,"Jun",Raw_Data!G2:G10) -> 1215000 | G10: =SUMIF(Raw_Data!B2:B10,"Jul",Raw_Data!G2:G10) -> 200000 | J10: =SUMIF(Reimbursements!E2:E4,"Pending",Reimbursements!D2:D4) -> 0
A11: Setup phase | D11: Launch prep | G11: Go-live | J11: Needs clearance

Sheet Pivot_Analysis
A1: PIVOT 1 — Category-Wise Expense Analysis
A2: Category | B2: Total Spend (₹) | C2: % of Total | D2: Tx Count | E2: Avg Spend (₹)
A3: Inventory Purchase | B3: =SUMIF(Raw_Data!D2:D10,A3,Raw_Data!G2:G10) -> 750000 | C3: =B3/SUM(Raw_Data!G2:G10) -> 0.39308176 | D3: =COUNTIF(Raw_Data!D2:D10,A3) -> 1 | E3: =IFERROR(B3/D3,0) -> 750000
A4: Product Photography | B4: =SUMIF(Raw_Data!D2:D10,A4,Raw_Data!G2:G10) -> 320000 | C4: =B4/SUM(Raw_Data!G2:G10) -> 0.16771488 | D4: =COUNTIF(Raw_Data!D2:D10,A4) -> 1 | E4: =IFERROR(B4/D4,0) -> 320000
A5: Website Development | B5: =SUMIF(Raw_Data!D2:D10,A5,Raw_Data!G2:G10) -> 250000 | C5: =B5/SUM(Raw_Data!G2:G10) -> 0.13102725 | D5: =COUNTIF(Raw_Data!D2:D10,A5) -> 1 | E5: =IFERROR(B5/D5,0) -> 250000
A6: Marketing | B6: =SUMIF(Raw_Data!D2:D10,A6,Raw_Data!G2:G10) -> 200000 | C6: =B6/SUM(Raw_Data!G2:G10) -> 0.1048218 | D6: =COUNTIF(Raw_Data!D2:D10,A6) -> 1 | E6: =IFERROR(B6/D6,0) -> 200000
A7: Recruitment | B7: =SUMIF(Raw_Data!D2:D10,A7,Raw_Data!G2:G10) -> 120000 | C7: =B7/SUM(Raw_Data!G2:G10) -> 0.062893082 | D7: =COUNTIF(Raw_Data!D2:D10,A7) -> 1 | E7: =IFERROR(B7/D7,0) -> 120000
A8: Logistics Setup | B8: =SUMIF(Raw_Data!D2:D10,A8,Raw_Data!G2:G10) -> 110000 | C8: =B8/SUM(Raw_Data!G2:G10) -> 0.057651992 | D8: =COUNTIF(Raw_Data!D2:D10,A8) -> 1 | E8: =IFERROR(B8/D8,0) -> 110000
A9: Branding | B9: =SUMIF(Raw_Data!D2:D10,A9,Raw_Data!G2:G10) -> 75000 | C9: =B9/SUM(Raw_Data!G2:G10) -> 0.039308176 | D9: =COUNTIF(Raw_Data!D2:D10,A9) -> 1 | E9: =IFERROR(B9/D9,0) -> 75000
A10: Domain & Hosting | B10: =SUMIF(Raw_Data!D2:D10,A10,Raw_Data!G2:G10) -> 48000 | C10: =B10/SUM(Raw_Data!G2:G10) -> 0.025157233 | D10: =COUNTIF(Raw_Data!D2:D10,A10) -> 1 | E10: =IFERROR(B10/D10,0) -> 48000
A11: Payment Gateway | B11: =SUMIF(Raw_Data!D2:D10,A11,Raw_Data!G2:G10) -> 35000 | C11: =B11/SUM(Raw_Data!G2:G10) -> 0.018343816 | D11: =COUNTIF(Raw_Data!D2:D10,A11) -> 1 | E11: =IFERROR(B11/D11,0) -> 35000
A12: GRAND TOTAL | B12: =SUM(B3:B11) -> 1908000 | C12: =SUM(C3:C11) -> 1 | D12: =SUM(D3:D11) -> 9 | E12: =IFERROR(B12/D12,0) -> 212000
A14: PIVOT 2 — Monthly Expense Trend
A15: Month | B15: Total Spend (₹) | C15: % of Total | D15: Tx Count | E15: MoM Change
A16: May | B16: =SUMIF(Raw_Data!B2:B10,A16,Raw_Data!G2:G10) -> 493000 | C16: =B16/SUM(Raw_Data!G2:G10) -> 0.25838574 | D16: =COUNTIF(Raw_Data!B2:B10,A16) -> 4 | E16: ="-" -> -
A17: Jun | B17: =SUMIF(Raw_Data!B2:B10,A17,Raw_Data!G2:G10) -> 1215000 | C17: =B17/SUM(Raw_Data!G2:G10) -> 0.63679245 | D17: =COUNTIF(Raw_Data!B2:B10,A17) -> 4 | E17: =IFERROR((B17-B16)/B16,0) -> 1.464503
A18: Jul | B18: =SUMIF(Raw_Data!B2:B10,A18,Raw_Data!G2:G10) -> 200000 | C18: =B18/SUM(Raw_Data!G2:G10) -> 0.1048218 | D18: =COUNTIF(Raw_Data!B2:B10,A18) -> 1 | E18: =IFERROR((B18-B17)/B17,0) -> -0.83539095
A21: PIVOT 3 — Payment Mode Analysis
A22: Payment Mode | B22: Total (₹) | C22: % Share | D22: Tx Count
A23: Bank Transfer | B23: =SUMIF(Raw_Data!H2:H10,A23,Raw_Data!G2:G10) -> 800000 | C23: =B23/SUM(Raw_Data!G2:G10) -> 0.41928721 | D23: =COUNTIF(Raw_Data!H2:H10,A23) -> 4
A24: RTGS | B24: =SUMIF(Raw_Data!H2:H10,A24,Raw_Data!G2:G10) -> 750000 | C24: =B24/SUM(Raw_Data!G2:G10) -> 0.39308176 | D24: =COUNTIF(Raw_Data!H2:H10,A24) -> 1
A25: Credit Card | B25: =SUMIF(Raw_Data!H2:H10,A25,Raw_Data!G2:G10) -> 248000 | C25: =B25/SUM(Raw_Data!G2:G10) -> 0.12997904 | D25: =COUNTIF(Raw_Data!H2:H10,A25) -> 2
A26: UPI | B26: =SUMIF(Raw_Data!H2:H10,A26,Raw_Data!G2:G10) -> 110000 | C26: =B26/SUM(Raw_Data!G2:G10) -> 0.057651992 | D26: =COUNTIF(Raw_Data!H2:H10,A26) -> 2

Sheet Formula_Analysis
A1: FORMULA ANALYSIS — SUMIFS / COUNTIFS / AVERAGEIFS / XLOOKUP / IF
A3: A. SUMIFS — Conditional Spend Aggregations
A4: Formula Description | B4: Criteria 1 | C4: Criteria 2 | D4: Result (₹) | E4: Formula Used
A5: Spend in May via Bank Transfer | B5: May | C5: Bank Transfer | D5: =SUMIFS(Raw_Data!G2:G10,Raw_Data!B2:B10,"May",Raw_Data!H2:H10,"Bank Transfer") -> 370000 | E5: =SUMIFS(G2:G10,B2:B10,"May",H2:H10,"Bank Transfer") -> 0
A6: Jun spend on Launch Prep phase | B6: Jun | C6: Launch Prep | D6: =SUMIFS(Raw_Data!G2:G10,Raw_Data!B2:B10,"Jun",Raw_Data!I2:I10,"Launch Prep") -> 1215000 | E6: =SUMIFS(G2:G10,B2:B10,"Jun",I2:I10,"Launch Prep") -> 0
A7: All Credit Card expenses | B7: Credit Card | C7: (any) | D7: =SUMIF(Raw_Data!H2:H10,"Credit Card",Raw_Data!G2:G10) -> 248000 | E7: =SUMIF(H2:H10,"Credit Card",G2:G10) -> 0
A8: Setup phase total spend | B8: Setup | C8: (any) | D8: =SUMIF(Raw_Data!I2:I10,"Setup",Raw_Data!G2:G10) -> 493000 | E8: =SUMIF(I2:I10,"Setup",G2:G10) -> 0
A11: B. COUNTIFS — Transaction Counts
A12: Description | B12: Criteria | C12: Count | D12: Formula Used
A13: Transactions in June | B13: Month=Jun | C13: =COUNTIF(Raw_Data!B2:B10,"Jun") -> 4 | D13: =COUNTIF(B2:B10,"Jun") -> 1
A14: Transactions via RTGS | B14: Mode=RTGS | C14: =COUNTIF(Raw_Data!H2:H10,"RTGS") -> 1 | D14: =COUNTIF(H2:H10,"RTGS") -> 0
A15: Transactions above ₹1,00,000 | B15: Amount>100K | C15: =COUNTIF(Raw_Data!G2:G10,">100000") -> 6 | D15: =COUNTIF(G2:G10,">100000") -> 0
A16: Transactions in Go-Live phase | B16: Phase=Go-Live | C16: =COUNTIF(Raw_Data!I2:I10,"Go-Live") -> 1 | D16: =COUNTIF(I2:I10,"Go-Live") -> 0
A19: C. AVERAGEIFS — Conditional Averages
A20: Description | B20: Criteria | C20: Average (₹) | D20: Formula Used
A21: Avg spend in Setup phase | B21: Phase=Setup | C21: =AVERAGEIF(Raw_Data!I2:I10,"Setup",Raw_Data!G2:G10) -> 123250 | D21: '=AVERAGEIF(I2:I10,"Setup",G2:G10)
A22: Avg spend via Bank Transfer | B22: Mode=Bank Transfer | C22: =AVERAGEIF(Raw_Data!H2:H10,"Bank Transfer",Raw_Data!G2:G10) -> 200000 | D22: '=AVERAGEIF(H2:H10,"Bank Transfer",G2:G10)
A23: Overall average transaction | B23: All | C23: =AVERAGE(Raw_Data!G2:G10) -> 212000 | D23: '=AVERAGE(G2:G10)
A26: D. INDEX/MATCH + IF — Vendor Lookup & Spend Flags (Excel: use XLOOKUP)
A27: Vendor | B27: Amount (₹) | C27: Category | D27: Spend Flag (IF) | E27: Phase
A28: PixelCraft Technologies | B28: =IFERROR(INDEX(Raw_Data!G$2:G$10,MATCH(A28,Raw_Data!E$2:E$10,0)),"Not Found") -> 250000 | C28: =IFERROR(INDEX(Raw_Data!D$2:D$10,MATCH(A28,Raw_Data!E$2:E$10,0)),"Unknown") -> Website Development | D28: =IF(B28>200000,"🔴 High Spend",IF(B28>100000,"🟡 Medium","🟢 Low")) -> 🔴 High Spend | E28: =IFERROR(INDEX(Raw_Data!I$2:I$10,MATCH(A28,Raw_Data!E$2:E$10,0)),"N/A") -> Setup
A29: Studio Vogue | B29: =IFERROR(INDEX(Raw_Data!G$2:G$10,MATCH(A29,Raw_Data!E$2:E$10,0)),"Not Found") -> 320000 | C29: =IFERROR(INDEX(Raw_Data!D$2:D$10,MATCH(A29,Raw_Data!E$2:E$10,0)),"Unknown") -> Product Photography | D29: =IF(B29>200000,"🔴 High Spend",IF(B29>100000,"🟡 Medium","🟢 Low")) -> 🔴 High Spend | E29: =IFERROR(INDEX(Raw_Data!I$2:I$10,MATCH(A29,Raw_Data!E$2:E$10,0)),"N/A") -> Launch Prep
A30: UrbanTex Suppliers | B30: =IFERROR(INDEX(Raw_Data!G$2:G$10,MATCH(A30,Raw_Data!E$2:E$10,0)),"Not Found") -> 750000 | C30: =IFERROR(INDEX(Raw_Data!D$2:D$10,MATCH(A30,Raw_Data!E$2:E$10,0)),"Unknown") -> Inventory Purchase | D30: =IF(B30>200000,"🔴 High Spend",IF(B30>100000,"🟡 Medium","🟢 Low")) -> 🔴 High Spend | E30: =IFERROR(INDEX(Raw_Data!I$2:I$10,MATCH(A30,Raw_Data!E$2:E$10,0)),"N/A") -> Launch Prep
A31: Meta Ads India | B31: =IFERROR(INDEX(Raw_Data!G$2:G$10,MATCH(A31,Raw_Data!E$2:E$10,0)),"Not Found") -> 200000 | C31: =IFERROR(INDEX(Raw_Data!D$2:D$10,MATCH(A31,Raw_Data!E$2:E$10,0)),"Unknown") -> Marketing | D31: =IF(B31>200000,"🔴 High Spend",IF(B31>100000,"🟡 Medium","🟢 Low")) -> 🟡 Medium | E31: =IFERROR(INDEX(Raw_Data!I$2:I$10,MATCH(A31,Raw_Data!E$2:E$10,0)),"N/A") -> Go-Live
A32: HireSphere HR | B32: =IFERROR(INDEX(Raw_Data!G$2:G$10,MATCH(A32,Raw_Data!E$2:E$10,0)),"Not Found") -> 120000 | C32: =IFERROR(INDEX(Raw_Data!D$2:D$10,MATCH(A32,Raw_Data!E$2:E$10,0)),"Unknown") -> Recruitment | D32: =IF(B32>200000,"🔴 High Spend",IF(B32>100000,"🟡 Medium","🟢 Low")) -> 🟡 Medium | E32: =IFERROR(INDEX(Raw_Data!I$2:I$10,MATCH(A32,Raw_Data!E$2:E$10,0)),"N/A") -> Setup

Sheet Charts
A1: CHARTS & VISUALIZATIONS — Expense Analysis
A3: Category | B3: Amount (₹) | K3: Month | L3: Amount (₹)
A4: Inventory | B4: =Pivot_Analysis!B3 -> 750000 | K4: May | L4: =Pivot_Analysis!B16 -> 493000
A5: Photography | B5: =Pivot_Analysis!B4 -> 320000 | K5: June | L5: =Pivot_Analysis!B17 -> 1215000
A6: Website Dev | B6: =Pivot_Analysis!B5 -> 250000 | K6: July | L6: =Pivot_Analysis!B18 -> 200000
A7: Marketing | B7: =Pivot_Analysis!B6 -> 200000
A8: Recruitment | B8: =Pivot_Analysis!B7 -> 120000
A9: Logistics | B9: =Pivot_Analysis!B8 -> 110000
A10: Branding | B10: =Pivot_Analysis!B9 -> 75000
A11: Hosting | B11: =Pivot_Analysis!B10 -> 48000
A12: Pay. Gateway | B12: =Pivot_Analysis!B11 -> 35000
A35: Payment Mode | B35: Amount (₹)
A36: Bank Transfer | B36: =Pivot_Analysis!B26 -> 110000
A37: RTGS | B37: =Pivot_Analysis!B27 -> 0
A38: Credit Card | B38: =Pivot_Analysis!B28 -> 0
A39: UPI | B39: =Pivot_Analysis!B29 -> 0

Sheet Receipts
A1: RECEIPTS REGISTER — GST & Compliance Tracker
A2: Receipt ID | B2: Vendor | C2: Date | D2: Service | E2: Amount Paid (₹) | F2: GST (₹) | G2: Total (₹) | H2: Status
A3: SN-001 | B3: PixelCraft Technologies | C3: 2026-05-05 | D3: Website UI/UX Design Advance | E3: 250000 | F3: 45000 | G3: =E3+F3 -> 295000 | H3: Paid
A4: SN-002 | B4: Studio Vogue | C4: 2026-06-02 | D4: Product Photography for Launch | E4: 320000 | F4: 57600 | G4: =E4+F4 -> 377600 | H4: Paid
A5: SN-003 | B5: Meta Ads India | C5: 2026-07-05 | D5: Social Media Launch Campaign | E5: 200000 | F5: 0 | G5: =E5+F5 -> 200000 | H5: ⚠ Missing GST
A6: TOTALS | E6: =SUM(E3:E5) -> 770000 | F6: =SUM(F3:F5) -> 102600 | G6: =SUM(G3:G5) -> 872600
A8: ⚠ ACTION REQUIRED: SN-003 (Meta Ads India) has no GST recorded. Potential ITC of ₹36,000 (18%) unclaimed. Request corrected invoice immediately.

Sheet Reimbursements
A1: EMPLOYEE REIMBURSEMENTS TRACKER
A2: Employee | B2: Department | C2: Purpose | D2: Amount (₹) | E2: Status | F2: Flag
A3: Riya Sharma | B3: Marketing | C3: Vendor meeting travel | D3: 8500 | E3: Approved | F3: =IF(E3="Pending","🔴 Action Needed",IF(E3="Approved","🟡 Awaiting Payment","🟢 Done")) -> 🟡 Awaiting Payment
A4: Aman Verma | B4: Operations | C4: Packaging samples | D4: 5200 | E4: Reimbursed | F4: =IF(E4="Pending","🔴 Action Needed",IF(E4="Approved","🟡 Awaiting Payment","🟢 Done")) -> 🟢 Done
A5: Neha Singh | B5: Tech Team | C5: SaaS testing tools | D5: 3400 | E5: Pending | F5: =IF(E5="Pending","🔴 Action Needed",IF(E5="Approved","🟡 Awaiting Payment","🟢 Done")) -> 🔴 Action Needed
A6: Total Claimed | D6: =SUM(D3:D5) -> 17100
A7: Total Reimbursed | D7: =SUMIF(E3:E5,"Reimbursed",D3:D5) -> 5200
A8: Total Pending | D8: =SUMIF(E3:E5,"Pending",D3:D5) -> 3400

Sheet Insights_Recommendations
A1: EXECUTIVE INSIGHTS & BUSINESS RECOMMENDATIONS
A3: KEY INSIGHTS FROM DATA
A4: # | B4: Insight | C4: Category | D4: Priority | E4: Formula Evidence | F4: Action Required
A5: 1 | B5: Inventory = 39.3% of total spend — single largest cost | C5: Spend Mix | D5: 🔴 Critical | E5: =Pivot_Analysis!B3/Pivot_Analysis!B12 -> 0.39308176 | F5: Get GRN/delivery note from UrbanTex
A6: 2 | B6: June spend ₹12.15L = 63.7% of all spend in one month | C6: Cash Flow | D6: 🔴 Critical | E6: =Pivot_Analysis!B17/KPI_Summary!A6 -> 0.63679245 | F6: Monitor burn rate weekly
A7: 3 | B7: Only 33% receipt coverage (3 of 9 transactions) | C7: Compliance | D7: 🔴 Critical | E7: =Receipts!E6/SUM(Raw_Data!G2:G10) -> 0.40356394 | F7: Enforce receipt policy immediately
A8: 4 | B8: GST missing on Meta Ads ₹2L — ITC risk of ₹36,000 | C8: Tax | D8: 🟡 High | E8: =Receipts!F5 -> 0 | F8: Request corrected invoice SN-003
A9: 5 | B9: Marketing is only 10.5% of spend for a 500-SKU launch | C9: Strategy | D9: 🟡 High | E9: =Pivot_Analysis!B6/Pivot_Analysis!B12 -> 0.1048218 | F9: Increase to ₹5–8L/month
A10: 6 | B10: Photography at ₹640/SKU — above industry avg ₹150-400 | C10: Cost Opt. | D10: 🟡 Medium | E10: =320000/500 -> 640 | F10: Get competitive quotes next shoot
A11: 7 | B11: ₹3,400 reimbursement pending — no SLA enforced | C11: Process | D11: 🟢 Low | E11: =Reimbursements!D8 -> 3400 | F11: Set 5-day reimbursement SLA
A12: 8 | B12: 81% of payments via Bank Transfer/RTGS — good traceability | C12: Positive | D12: 🟢 Info | E12: =SUMIFS(Raw_Data!G2:G10,Raw_Data!H2:H10,"Bank Transfer")+SUMIFS(Raw_Data!G2:G10,Raw_Data!H2:H10,"RTGS") -> 1550000 | F12: Maintain this payment discipline
A15: BUSINESS RECOMMENDATIONS
A16: Priority | B16: Recommendation | C16: Department | D16: Timeline | E16: Expected Impact | F16: KPI to Track
A17: 1 — Immediate | B17: Implement mandatory receipt policy for all vendor payments | C17: Finance | D17: This week | E17: Full audit readiness; ITC capture | F17: Receipt coverage %
A18: 2 — Immediate | B18: Request corrected GST invoice from Meta Ads India | C18: Finance | D18: 48 hours | E18: Recover ₹36,000 ITC | F18: GST reconciliation
A19: 3 — This month | B19: Obtain GRN/delivery confirmation from UrbanTex Suppliers | C19: Operations | D19: 2 weeks | E19: Inventory risk mitigation | F19: Inventory receipt status
A20: 4 — Month 2 | B20: Increase marketing budget to ₹5–8L/month for D2C launch | C20: Marketing | D20: Month 2 | E20: Customer acquisition & revenue | F20: CAC, ROAS, Revenue
A21: 5 — Month 2 | B21: Get 3 competitive quotes for next photography shoot | C21: Operations | D21: Before next shoot | E21: Save ₹1–2L on photography | F21: Cost per SKU
A22: 6 — Ongoing | B22: Set 5-business-day reimbursement SLA for employees | C22: HR/Finance | D22: Immediately | E22: Employee satisfaction + cash flow | F22: Pending reimbursements

Sheet Dashboard_Guide
A1: EXCEL DASHBOARD GUIDE — Step-by-Step Instructions
A3: STEP 1: CREATE PIVOT TABLE — Category Analysis
A4: 1. Click on Raw_Data sheet → Select A1:I10 → Insert → PivotTable 2. Place in new sheet named 'PT_Category' 3. Drag 'Category' to Rows | 'Amount' to Values (Sum) 4. Right-click Amount → Value Field Settings → Number Format → Currency 5. Add 'Payment_Mode' to Filters for drill-down
A9: STEP 2: CREATE PIVOT TABLE — Monthly Trend
A10: 1. Insert → PivotTable from Raw_Data → place in 'PT_Monthly' 2. Drag 'Month' to Rows | 'Amount' to Values | 'Phase' to Filters 3. Sort Month by Month_Num column for correct order 4. Add calculated field: Cumulative Spend = Running Total in Amount
A15: STEP 3: CREATE BAR CHART from Pivot
A16: 1. Click inside PT_Category pivot table 2. PivotTable Analyze → PivotChart → Clustered Bar → OK 3. Format: Chart Title = 'Expense by Category' | Remove gridlines 4. Change bar color to #2E75B6 | Add data labels
A21: STEP 4: CREATE LINE CHART — Monthly Trend
A22: 1. Click inside PT_Monthly pivot table 2. PivotTable Analyze → PivotChart → Line with Markers 3. Format: Title = 'Monthly Spend Trend' | Y-axis = Currency format 4. Add trendline: Right-click line → Add Trendline → Linear
A27: STEP 5: CREATE PIE CHART — Payment Mode
A28: 1. Select Charts!A35:B39 (payment mode data) 2. Insert → Chart → Pie → 2-D Pie 3. Add data labels showing percentage 4. Format each slice with distinct colours
A33: STEP 6: ADD SLICERS
... A52: 1. Review → Protect Sheet on Raw_Data (allow filter only) 2. Lock formula cells in KPI_Summary and Pivot_Analysis 3. File → Properties → add Title, Author, Company 4. Save as .xlsm if using macros, .xlsx otherwise
